fp_alu.v

`timescale 1ns / 1ps

module fp_alu(
    input clk,
    input reset,
    input start,
    input [31:0] operand_a,
    input [31:0] operand_b,
    input [2:0] opcode,
    output reg [31:0] result,
    output reg invalid,
    output reg ready
);

    // Opcodes
    localparam OP_ADD = 3'b000;
    localparam OP_SUB = 3'b001;
    localparam OP_MUL = 3'b010;
    localparam OP_DIV = 3'b011;

    // FSM states
    localparam IDLE = 3'd0;
    localparam UNPACK = 3'd1;
    localparam CALCULATE = 3'd2;
    localparam NORMALIZE = 3'd3;
    localparam ROUND = 3'd4;
    localparam PACK = 3'd5;
    localparam DONE = 3'd6;

    reg [2:0] state = IDLE;

    // Operands unpacked
    reg sign_a, sign_b;
    reg [7:0] exp_a, exp_b;
    reg [23:0] man_a, man_b;

    // Intermediate result
    reg sign_res;
    reg [8:0] exp_res;
    reg [47:0] man_res;
    
    // For division
    reg [47:0] quotient;
    reg [48:0] remainder;


    always @(posedge clk or posedge reset) begin
        if (reset) begin
            state <= IDLE;
            ready <= 1;
            invalid <= 0;
            result <= 0;
        end else begin
            case (state)
                IDLE: begin
                    if (start && ready) begin
                        ready <= 0;
                        state <= UNPACK;
                    end
                end
                
                UNPACK: begin
                    sign_a <= operand_a[31];
                    exp_a  <= operand_a[30:23];
                    man_a  <= (operand_a[30:0] == 0) ? 24'd0 : {1'b1, operand_a[22:0]};

                    sign_b <= operand_b[31];
                    exp_b  <= operand_b[30:23];
                    man_b  <= (operand_b[30:0] == 0) ? 24'd0 : {1'b1, operand_b[22:0]};
                    state <= CALCULATE;
                end
                
                CALCULATE: begin
                    invalid <= 0;
                    case (opcode)
                        OP_ADD, OP_SUB: fp_add_sub();
                        OP_MUL: fp_multiply();
                        OP_DIV: fp_divide();
                    endcase
                    state <= NORMALIZE;
                end

                NORMALIZE: begin
                    normalize();
                    state <= ROUND;
                end

                ROUND: begin
                    round_result();
                    state <= PACK;
                end
                
                PACK: begin
                    result <= {sign_res, exp_res[7:0], man_res[22:0]};
                    state <= DONE;
                end

                DONE: begin
                    ready <= 1;
                    state <= IDLE;
                end
            endcase
        end
    end

    task fp_add_sub;
        reg [8:0] exp_a_ext, exp_b_ext;
        reg [25:0] man_a_ext, man_b_ext;
        reg [8:0] exp_diff;
        reg sign_b_eff;
        reg [26:0] man_res_addsub;
    begin
        exp_a_ext = {1'b0, exp_a};
        exp_b_ext = {1'b0, exp_b};
        man_a_ext = {man_a, 2'b00};
        man_b_ext = {man_b, 2'b00};

        if (exp_a_ext > exp_b_ext) begin
            exp_diff = exp_a_ext - exp_b_ext;
            man_b_ext = man_b_ext >> exp_diff;
            exp_res = exp_a_ext;
        end else begin
            exp_diff = exp_b_ext - exp_a_ext;
            man_a_ext = man_a_ext >> exp_diff;
            exp_res = exp_b_ext;
        end

        sign_b_eff = sign_b ^ (opcode == OP_SUB);

        if (sign_a == sign_b_eff) begin // Effective addition
            man_res_addsub = {1'b0, man_a_ext} + {1'b0, man_b_ext};
            sign_res = sign_a;
        end else begin // Effective subtraction
            if (man_a_ext >= man_b_ext) begin
                man_res_addsub = man_a_ext - man_b_ext;
                sign_res = sign_a;
            end else begin
                man_res_addsub = man_b_ext - man_a_ext;
                sign_res = sign_b_eff;
            end
        end
        man_res = man_res_addsub << 21;
    end
    endtask
    
    task fp_multiply;
    begin
        sign_res = sign_a ^ sign_b;
        exp_res = exp_a + exp_b - 127;
        man_res = man_a * man_b;
    end
    endtask

    task fp_divide;
    begin
        if (|man_b == 0) begin // Division by zero
            invalid <= 1;
            man_res <= 48'd0;
            exp_res <= 9'd0;
            sign_res <= 1'b0;
        end else begin
            sign_res = sign_a ^ sign_b;
            exp_res = exp_a - exp_b + 127;
            fp_divide_iter({man_a, 25'd0}, man_b);
            man_res = quotient << 21;
        end
    end
    endtask
    
    task fp_divide_iter;
        input [48:0] dividend;
        input [23:0] divisor;
        integer i;
    begin
        remainder = dividend;
        quotient = 0;

        for (i=0; i<25; i=i+1) begin
            remainder = remainder << 1;
            if (remainder[48:24] >= divisor) begin
                remainder[48:24] = remainder[48:24] - divisor;
                quotient[24-i] = 1;
            end
        end
    end
    endtask

    task normalize;
    begin
        if (man_res == 0) begin
            exp_res = 0;
        end else if (man_res >= {2'b10, 46'd0}) begin
            while (man_res >= {2'b10, 46'd0}) begin
                 man_res = man_res >> 1;
                 exp_res = exp_res + 1;
            end
        end else begin
            while (man_res < {2'b01, 46'd0}) begin
                man_res = man_res << 1;
                exp_res = exp_res - 1;
            end
        end
    end
    endtask
    
    task round_result;
        reg round_bit;
    begin
        round_bit = man_res[22];
        man_res = (man_res >> 23) + round_bit;

        if (man_res >= {2'b10, 23'd0}) begin
            man_res = man_res >> 1;
            exp_res = exp_res + 1;
        end
    end
    endtask

endmodule

fp_alu_tb.v
// ============================================================================
// Testbench
// ============================================================================
module fp_alu_tb;
    reg clk;
    reg reset;
    reg [31:0] operand_a;
    reg [31:0] operand_b;
    reg [2:0] opcode;
    reg start;
    wire [31:0] result;
    wire ready;
    wire invalid;
    
    fp_alu uut (
        .clk(clk),
        .reset(reset),
        .start(start),
        .operand_a(operand_a),
        .operand_b(operand_b),
        .opcode(opcode),
        .result(result),
        .ready(ready),
        .invalid(invalid)
    );
    
    // Clock generation
    initial begin
        clk = 0;
        forever #5 clk = ~clk;
    end
    
    // Test cases
    initial begin
        $dumpfile("fp_alu.vcd");
        $dumpvars(0, fp_alu_tb);
        
        // Initialize
        reset = 1;
        start = 0;
        #20 reset = 0;
        
        // Test 1: Addition - 3.5 + 2.25 = 5.75
        wait(ready);
        #10;
        operand_a = 32'h40600000; // 3.5
        operand_b = 32'h40100000; // 2.25
        opcode = 3'b000; // ADD
        start = 1;
        #10 start = 0;
        wait(ready);
        $display("Test 1 - ADD: 3.5 + 2.25 = %h (Expected: 40B80000)", result);
        
        // Test 2: Subtraction - 10.0 - 3.0 = 7.0
        wait(ready);
        #10;
        operand_a = 32'h41200000; // 10.0
        operand_b = 32'h40400000; // 3.0
        opcode = 3'b001; // SUB
        start = 1;
        #10 start = 0;
        wait(ready);
        $display("Test 2 - SUB: 10.0 - 3.0 = %h (Expected: 40E00000)", result);
        
        // Test 3: Multiplication - 2.5 * 4.0 = 10.0
        wait(ready);
        #10;
        operand_a = 32'h40200000; // 2.5
        operand_b = 32'h40800000; // 4.0
        opcode = 3'b010; // MUL
        start = 1;
        #10 start = 0;
        wait(ready);
        $display("Test 3 - MUL: 2.5 * 4.0 = %h (Expected: 41200000)", result);
        
        // Test 4: Division - 10.0 / 2.0 = 5.0
        wait(ready);
        #10;
        operand_a = 32'h41200000; // 10.0
        operand_b = 32'h40000000; // 2.0
        opcode = 3'b011; // DIV
        start = 1;
        #10 start = 0;
        wait(ready);
        $display("Test 4 - DIV: 10.0 / 2.0 = %h (Expected: 40A00000)", result);
        
        // Test 5: Division by zero
        wait(ready);
        #10;
        operand_a = 32'h40200000; // 2.5
        operand_b = 32'h00000000; // 0.0
        opcode = 3'b011; // DIV
        start = 1;
        #10 start = 0;
        wait(ready);
        $display("Test 5 - DIV by zero: Invalid=%b", invalid);
        
        #100;
        $finish;
    end
endmodule

fp_alu.vcd
$date
	Wed Dec 10 02:14:58 2025
$end
$version
	Icarus Verilog
$end
$timescale
	1ps
$end
$scope module fp_alu_tb $end
$var wire 32 ! result [31:0] $end
$var wire 1 " ready $end
$var wire 1 # invalid $end
$var reg 1 $ clk $end
$var reg 3 % opcode [2:0] $end
$var reg 32 & operand_a [31:0] $end
$var reg 32 ' operand_b [31:0] $end
$var reg 1 ( reset $end
$var reg 1 ) start $end
$scope module uut $end
$var wire 1 $ clk $end
$var wire 3 * opcode [2:0] $end
$var wire 32 + operand_a [31:0] $end
$var wire 32 , operand_b [31:0] $end
$var wire 1 ( reset $end
$var wire 1 ) start $end
$var parameter 3 - CALCULATE $end
$var parameter 3 . DONE $end
$var parameter 3 / IDLE $end
$var parameter 3 0 NORMALIZE $end
$var parameter 3 1 OP_ADD $end
$var parameter 3 2 OP_DIV $end
$var parameter 3 3 OP_MUL $end
$var parameter 3 4 OP_SUB $end
$var parameter 3 5 PACK $end
$var parameter 3 6 ROUND $end
$var parameter 3 7 UNPACK $end
$var reg 8 8 exp_a [7:0] $end
$var reg 8 9 exp_b [7:0] $end
$var reg 9 : exp_res [8:0] $end
$var reg 1 # invalid $end
$var reg 24 ; man_a [23:0] $end
$var reg 24 < man_b [23:0] $end
$var reg 48 = man_res [47:0] $end
$var reg 48 > quotient [47:0] $end
$var reg 1 " ready $end
$var reg 49 ? remainder [48:0] $end
$var reg 32 @ result [31:0] $end
$var reg 1 A sign_a $end
$var reg 1 B sign_b $end
$var reg 1 C sign_res $end
$var reg 3 D state [2:0] $end
$scope task fp_add_sub $end
$var reg 9 E exp_a_ext [8:0] $end
$var reg 9 F exp_b_ext [8:0] $end
$var reg 9 G exp_diff [8:0] $end
$var reg 26 H man_a_ext [25:0] $end
$var reg 26 I man_b_ext [25:0] $end
$var reg 27 J man_res_addsub [26:0] $end
$var reg 1 K sign_b_eff $end
$upscope $end
$scope task fp_divide $end
$upscope $end
$scope task fp_divide_iter $end
$var reg 49 L dividend [48:0] $end
$var reg 24 M divisor [23:0] $end
$var integer 32 N i [31:0] $end
$upscope $end
$scope task fp_multiply $end
$upscope $end
$scope task normalize $end
$upscope $end
$scope task round_result $end
$var reg 1 O round_bit $end
$upscope $end
$upscope $end
$upscope $end
$enddefinitions $end
$comment Show the parameter values. $end
$dumpall
b1 7
b100 6
b101 5
b1 4
b10 3
b11 2
b0 1
b11 0
b0 /
b110 .
b10 -
$end
#0
$dumpvars
xO
bx N
bx M
bx L
xK
bx J
bx I
bx H
bx G
bx F
bx E
b0 D
xC
xB
xA
b0 @
bx ?
bx >
bx =
bx <
bx ;
bx :
bx 9
bx 8
bx ,
bx +
bx *
0)
1(
bx '
bx &
bx %
0$
0#
1"
b0 !
$end
#5000
1$
#10000
0$
#15000
1$
#20000
0$
0(
#25000
1$
#30000
0$
1)
b0 %
b0 *
b1000000000100000000000000000000 '
b1000000000100000000000000000000 ,
b1000000011000000000000000000000 &
b1000000011000000000000000000000 +
#35000
b1 D
0"
1$
#40000
0$
0)
#45000
b10 D
b100100000000000000000000 <
b10000000 9
0B
b111000000000000000000000 ;
b10000000 8
0A
1$
#50000
0$
#55000
b11 D
b101110000000000000000000000000000000000000000000 =
0C
b101110000000000000000000000 J
0K
b10000000 :
b0 G
b10010000000000000000000000 I
b11100000000000000000000000 H
b10000000 F
b10000000 E
1$
#60000
0$
#65000
b100 D
b10000001 :
b10111000000000000000000000000000000000000000000 =
1$
#70000
0$
#75000
b101 D
b101110000000000000000000 =
0O
1$
#80000
0$
#85000
b110 D
b1000000101110000000000000000000 !
b1000000101110000000000000000000 @
1$
#90000
0$
#95000
b0 D
1"
1$
#100000
0$
#105000
b1 D
0"
1$
1)
b1 %
b1 *
b1000000010000000000000000000000 '
b1000000010000000000000000000000 ,
b1000001001000000000000000000000 &
b1000001001000000000000000000000 +
#110000
0$
#115000
b10 D
b110000000000000000000000 <
b101000000000000000000000 ;
b10000010 8
1$
0)
#120000
0$
#125000
b11 D
b1110000000000000000000000000000000000000000000 =
b1110000000000000000000000 J
1K
b10000010 :
b10 G
b110000000000000000000000 I
b10100000000000000000000000 H
b10000010 E
1$
#130000
0$
#135000
b100 D
b10000001 :
b11100000000000000000000000000000000000000000000 =
1$
#140000
0$
#145000
b101 D
b111000000000000000000000 =
1$
#150000
0$
#155000
b110 D
b1000000111000000000000000000000 !
b1000000111000000000000000000000 @
1$
#160000
0$
#165000
b0 D
1"
1$
#170000
0$
#175000
b1 D
0"
1$
1)
b10 %
b10 *
b1000000100000000000000000000000 '
b1000000100000000000000000000000 ,
b1000000001000000000000000000000 &
b1000000001000000000000000000000 +
#180000
0$
#185000
b10 D
b100000000000000000000000 <
b10000001 9
b10000000 8
1$
0)
#190000
0$
#195000
b11 D
b10100000000000000000000000000000000000000000000 =
b10000010 :
1$
#200000
0$
#205000
b100 D
1$
#210000
0$
#215000
b101 D
b101000000000000000000000 =
1$
#220000
0$
#225000
b110 D
b1000001001000000000000000000000 !
b1000001001000000000000000000000 @
1$
#230000
0$
#235000
b0 D
1"
1$
#240000
0$
#245000
b1 D
0"
1$
1)
b11 %
b11 *
b1000000000000000000000000000000 '
b1000000000000000000000000000000 ,
b1000001001000000000000000000000 &
b1000001001000000000000000000000 +
#250000
0$
#255000
b10 D
b10000000 9
b10000010 8
1$
0)
#260000
0$
#265000
b11 D
b1000000000000000000000000000000000000000000000 =
b11001 N
b1000000000000000000000000 >
b0 ?
b100000000000000000000000 M
b1010000000000000000000000000000000000000000000000 L
b10000001 :
1$
#270000
0$
#275000
b100 D
b10000000 :
b10000000000000000000000000000000000000000000000 =
1$
#280000
0$
#285000
b101 D
b100000000000000000000000 =
1$
#290000
0$
#295000
b110 D
b1000000000000000000000000000000 !
b1000000000000000000000000000000 @
1$
#300000
0$
#305000
b0 D
1"
1$
#310000
0$
#315000
b1 D
0"
1$
1)
b0 '
b0 ,
b1000000001000000000000000000000 &
b1000000001000000000000000000000 +
#320000
0$
#325000
b10 D
b0 <
b0 9
b10000000 8
1$
0)
#330000
0$
#335000
b11 D
b0 :
b0 =
1#
1$
#340000
0$
#345000
b100 D
1$
#350000
0$
#355000
b101 D
1$
#360000
0$
#365000
b110 D
b0 !
b0 @
1$
#370000
0$
#375000
b0 D
1"
1$
